MianduiDuixiangBianchengyuyanYingyongHeJieshi/README.md
MianduiDuixiangBianchengyuyanYingyongHeJieshi/__init__.py
MianduiDuixiangBianchengyuyanYingyongHeJieshi/__main__.py
MianduiDuixiangBianchengyuyanYingyongHeJieshi/file.epub
MianduiDuixiangBianchengyuyanYingyongHeJieshi/index.html
MianduiDuixiangBianchengyuyanYingyongHeJieshi/css/__init__.py
MianduiDuixiangBianchengyuyanYingyongHeJieshi/css/annotations.css
MianduiDuixiangBianchengyuyanYingyongHeJieshi/css/main.css
MianduiDuixiangBianchengyuyanYingyongHeJieshi/css/normalize.css
MianduiDuixiangBianchengyuyanYingyongHeJieshi/css/popup.css
MianduiDuixiangBianchengyuyanYingyongHeJieshi/font/__init__.py
MianduiDuixiangBianchengyuyanYingyongHeJieshi/font/fontello.eot
MianduiDuixiangBianchengyuyanYingyongHeJieshi/font/fontello.svg
MianduiDuixiangBianchengyuyanYingyongHeJieshi/font/fontello.ttf
MianduiDuixiangBianchengyuyanYingyongHeJieshi/font/fontello.woff
MianduiDuixiangBianchengyuyanYingyongHeJieshi/img/__init__.py
MianduiDuixiangBianchengyuyanYingyongHeJieshi/img/annotator-glyph-sprite.png
MianduiDuixiangBianchengyuyanYingyongHeJieshi/img/annotator-icon-sprite.png
MianduiDuixiangBianchengyuyanYingyongHeJieshi/img/apple-touch-icon.png
MianduiDuixiangBianchengyuyanYingyongHeJieshi/img/cancelfullscreen.png
MianduiDuixiangBianchengyuyanYingyongHeJieshi/img/close.png
MianduiDuixiangBianchengyuyanYingyongHeJieshi/img/fullscreen.png
MianduiDuixiangBianchengyuyanYingyongHeJieshi/img/loader.gif
MianduiDuixiangBianchengyuyanYingyongHeJieshi/img/menu-icon.png
MianduiDuixiangBianchengyuyanYingyongHeJieshi/img/save.png
MianduiDuixiangBianchengyuyanYingyongHeJieshi/img/saved.png
MianduiDuixiangBianchengyuyanYingyongHeJieshi/img/settings-s.png
MianduiDuixiangBianchengyuyanYingyongHeJieshi/img/settings.png
MianduiDuixiangBianchengyuyanYingyongHeJieshi/img/star.png
MianduiDuixiangBianchengyuyanYingyongHeJieshi/js/__init__.py
MianduiDuixiangBianchengyuyanYingyongHeJieshi/js/epub.js
miandui_duixiang_bianchengyuyan_yingyong_he_jieshi-2024.3.3.0.dist-info/METADATA
miandui_duixiang_bianchengyuyan_yingyong_he_jieshi-2024.3.3.0.dist-info/WHEEL
miandui_duixiang_bianchengyuyan_yingyong_he_jieshi-2024.3.3.0.dist-info/entry_points.txt
miandui_duixiang_bianchengyuyan_yingyong_he_jieshi-2024.3.3.0.dist-info/top_level.txt
miandui_duixiang_bianchengyuyan_yingyong_he_jieshi-2024.3.3.0.dist-info/RECORD
